byzh/extra/__init__.py
byzh/extra/__main__.py
byzh/extra/home.py
byzh/extra/Bconvert/__init__.py
byzh/extra/Bconvert/img_pdf.py
byzh/extra/Bconvert/img_ppt.py
byzh/extra/Bconvert/ipynb_py.py
byzh/extra/Bconvert/mp4_ts.py
byzh/extra/Bcrawler/__init__.py
byzh/extra/Bcrawler/convert.py
byzh/extra/Bffmpeg/__init__.py
byzh/extra/Bffmpeg/convert.py
byzh/extra/Bffmpeg/merge.py
byzh/extra/Bfinder/__init__.py
byzh/extra/Bfinder/size.py
byzh/extra/Bfinder/txt.py
byzh/extra/Bm3u8/__init__.py
byzh/extra/Bm3u8/download.py
byzh/extra/Bm3u8/dual_VLC_player.py
byzh/extra/Bmarkdown/__init__.py
byzh/extra/Bmarkdown/make_catalog.py
byzh/extra/Bmathematical_modeling/AHP.py
byzh/extra/Bmathematical_modeling/EWM.py
byzh/extra/Bmathematical_modeling/TOPSIS.py
byzh/extra/Bmathematical_modeling/__init__.py
byzh/extra/Bmathematical_modeling/math_utils.py
byzh/extra/Bmine/__init__.py
byzh/extra/Bmine/screenshot.py
byzh/extra/Boffice/__init__.py
byzh/extra/Boffice/pdf.py
byzh/extra/h5py/__init__.py
byzh/extra/h5py/show.py
byzh/extra/pandas/__init__.py
byzh/extra/pandas/utils.py
byzh_extra-0.0.9.12.dist-info/LICENSE
byzh_extra-0.0.9.12.dist-info/METADATA
byzh_extra-0.0.9.12.dist-info/WHEEL
byzh_extra-0.0.9.12.dist-info/entry_points.txt
byzh_extra-0.0.9.12.dist-info/top_level.txt
byzh_extra-0.0.9.12.dist-info/RECORD
