Metadata-Version: 2.1
Name: byzh-extra
Version: 0.0.9.12
Summary: 基于byzh-core的扩展包
Author: byzh_rc
License: MIT
License-File: LICENSE
Requires-Dist: byzh-core>=0.0.9.0
Requires-Dist: python-pptx
Requires-Dist: pdf2image
Requires-Dist: chardet
Requires-Dist: fpdf2
Requires-Dist: beautifulsoup4
